drcutils/__init__.py
drcutils/brand.py
drcutils/cad.py
drcutils/colormaps.py
drcutils/env.py
drcutils/magic.py
drcutils/ml.py
drcutils/data/color_pattern.png
drcutils/data/drc.mplstyle
drcutils/data/grey_pattern.png
drcutils/data/horizontal.png
drcutils/data/logo.png
drcutils/data/logo.stl
drcutils/data/logo.svg
drcutils/data/stacked.png
drcutils/data/white_pattern.png
drcutils-0.1.0.dist-info/LICENSE
drcutils-0.1.0.dist-info/METADATA
drcutils-0.1.0.dist-info/WHEEL
drcutils-0.1.0.dist-info/top_level.txt
drcutils-0.1.0.dist-info/RECORD
